<?xml version='1.0' encoding='utf-8'?>
            <?xml-stylesheet version='1.0' href='../../stylesheets/contact2html.xsl' type='text/xsl'?>
            <contactDataSet xmlns='http://lca.jrc.it/ILCD/Contact' xmlns:common='http://lca.jrc.it/ILCD/Common' xmlns:xsi='http://www.w3.org/2001/XMLSchema-instance' xsi:schemaLocation='http://lca.jrc.it/ILCD/Contact ../../schemas/ILCD_ContactDataSet.xsd' version='1.1'>
              <contactInformation>
                <dataSetInformation>
                  <common:UUID>58671b99-d3a3-452f-880b-d3bfd7eb1003</common:UUID>
                  <common:name xml:lang='de'>Österreichisches Institut für Bauen und Ökologie GmbH</common:name>
                  <common:shortName xml:lang='de'>Österreichisches Institut für Bauen und Ökologie GmbH</common:shortName>
                  <contactAddress xml:lang='de'>Alserbachstraße 5/8, 1090 Wien, Austria</contactAddress>
                  <telephone>+43 13192005</telephone>
                  <telefax>+43 13192005-50</telefax>
                  <email>philipp.boogman@ibo.at</email>
                  <WWWAddress>www.ibo.at</WWWAddress>
                </dataSetInformation>
              </contactInformation>
              <administrativeInformation>
                <dataEntryBy>
                  <common:timeStamp>09.03.2016</common:timeStamp>
                </dataEntryBy>
                <publicationAndOwnership>
                  <common:dataSetVersion>00.01.000</common:dataSetVersion>
                </publicationAndOwnership>
              </administrativeInformation>
            </contactDataSet>
        