<?xml version='1.0' encoding='utf-8'?>
            <?xml-stylesheet version='1.0' href='../../stylesheets/contact2html.xsl' type='text/xsl'?>
            <contactDataSet xmlns='http://lca.jrc.it/ILCD/Contact' xmlns:common='http://lca.jrc.it/ILCD/Common' xmlns:xsi='http://www.w3.org/2001/XMLSchema-instance' xsi:schemaLocation='http://lca.jrc.it/ILCD/Contact ../../schemas/ILCD_ContactDataSet.xsd' version='1.1'>
              <contactInformation>
                <dataSetInformation>
                  <common:UUID>8ac54d9c-9919-4aba-8f9c-837b3225cd67</common:UUID>
                  <common:shortName xml:lang='de'>Holcim (Deutschland) GmbH</common:shortName>
                  <common:name xml:lang='de'>Holcim (Deutschland) GmbH</common:name>
                  <contactAddress xml:lang='de'>Willy-Brand-Straße 69, 20457 Hamburg, Germany</contactAddress>
                  <telephone>+49 (0)5132 927 432</telephone>
                  <telefax>+49 (0)5132 927 430</telefax>
                  <email>technisches-marketing@lafargeholcim.com</email>
                  <WWWAddress>www.holcim.de</WWWAddress>
                </dataSetInformation>
              </contactInformation>
              <administrativeInformation>
                <dataEntryBy>
                  <common:timeStamp>2020-02-27T15:16:07.3782344+01:00</common:timeStamp>
                </dataEntryBy>
                <publicationAndOwnership>
                  <common:dataSetVersion>00.01.000</common:dataSetVersion>
                </publicationAndOwnership>
              </administrativeInformation>
            </contactDataSet>
        