<?xml version="1.0" encoding="UTF-8" standalone="yes"?>
<s:sourceDataSet xmlns:m="http://lca.jrc.it/ILCD/LCIAMethod" xmlns:common="http://lca.jrc.it/ILCD/Common" xmlns:s="http://lca.jrc.it/ILCD/Source" xmlns:c="http://lca.jrc.it/ILCD/Contact" xmlns:f="http://lca.jrc.it/ILCD/Flow" xmlns="http://lca.jrc.it/ILCD/Process" xmlns:fp="http://lca.jrc.it/ILCD/FlowProperty" xmlns:u="http://lca.jrc.it/ILCD/UnitGroup" version="1.1">
    <s:sourceInformation>
        <s:dataSetInformation>
            <common:UUID>68261bd2-0e0f-4fb3-ae8b-48aedc97599c</common:UUID>
            <common:shortName xml:lang="de">EPD Isolierstege aus recycltem PA 66 GF 25</common:shortName>
            <common:shortName xml:lang="en">EPD Isolierstege aus recycltem PA 66 GF 25</common:shortName>
            <s:classificationInformation>
                <common:classification>
                    <common:class level="0" classId="8ee3821d-1653-4bfa-8bcf-3fe27f05e8f1">EPDs</common:class>
                </common:classification>
            </s:classificationInformation>
            <s:sourceDescriptionOrComment xml:lang="en"></s:sourceDescriptionOrComment>
            <s:referenceToDigitalFile uri="../external_docs/2019-08-20_ift_EPD_Technoform_PA6.6GF25REC.pdf"/>
            <s:referenceToContact type="contact data set" refObjectId="c2c59299-ef29-4110-8815-5b1f93cb528b" version="00.00.002" uri="http://openlca.org/ilcd/resource/contacts/c2c59299-ef29-4110-8815-5b1f93cb528b">
                <common:shortDescription xml:lang="de">Technoform Bautec Kunststoffprodukte GmbH</common:shortDescription>
                <common:shortDescription xml:lang="en">Technoform Bautec Kunststoffprodukte GmbH</common:shortDescription>
            </s:referenceToContact>
        </s:dataSetInformation>
    </s:sourceInformation>
    <s:administrativeInformation>
        <s:dataEntryBy>
            <common:timeStamp>2019-08-21T11:29:36.531+02:00</common:timeStamp>
            <common:referenceToDataSetFormat type="source data set" refObjectId="a97a0155-0234-4b87-b4ce-a45da52f2a40" version="01.01.000" uri="../sources/a97a0155-0234-4b87-b4ce-a45da52f2a40_01.01.000.xml">
                <common:shortDescription xml:lang="en">ILCD format</common:shortDescription>
            </common:referenceToDataSetFormat>
        </s:dataEntryBy>
        <s:publicationAndOwnership>
            <common:dataSetVersion>00.00.002</common:dataSetVersion>
            <common:permanentDataSetURI>http://openlca.org/ilcd/resource/sources/68261bd2-0e0f-4fb3-ae8b-48aedc97599c</common:permanentDataSetURI>
        </s:publicationAndOwnership>
    </s:administrativeInformation>
</s:sourceDataSet>
