<?xml version='1.0' encoding='utf-8'?>
            <?xml-stylesheet version='1.0' href='../../stylesheets/source2html.xsl' type='text/xsl'?>
            <sourceDataSet xmlns='http://lca.jrc.it/ILCD/Source' xmlns:common='http://lca.jrc.it/ILCD/Common' xmlns:xsi='http://www.w3.org/2001/XMLSchema-instance' xsi:schemaLocation='http://lca.jrc.it/ILCD/Source ../../schemas/ILCD_SourceDataSet.xsd' version='1.1'>
              <sourceInformation>
                <dataSetInformation>
                  <common:UUID>8552e18f-a1ba-48e1-9188-fc820e4aa3be</common:UUID>
                  <common:shortName xml:lang='de'>EPD-Dokument Mehrschichtparkett_9683.pdf</common:shortName>
                  <referenceToDigitalFile uri='Mehrschichtparkett_9683.pdf'/>
                </dataSetInformation>
              </sourceInformation>
              <administrativeInformation>
                <dataEntryBy>
                  <common:timeStamp>2020-08-24T14:29:55.9837915+02:00</common:timeStamp>
                </dataEntryBy>
                <publicationAndOwnership>
                  <common:dataSetVersion>00.08.000</common:dataSetVersion>
                </publicationAndOwnership>
              </administrativeInformation>
            </sourceDataSet>
        